[
  {
    "line": 2,
    "elements": [
      {
        "start_timestamp": "2021-11-11T08:50:50.687Z",
        "before": [
          {
            "result": {
              "duration": 3998900,
              "status": "passed"
            },
            "match": {
              "location": "stepdefinitions.Hooks.setUp()"
            }
          }
        ],
        "line": 5,
        "name": "TC07 Istenen kelimenin oldugunu test etme",
        "description": "",
        "id": "us1003-kullanici-istedigi-kelime-icin-arama-yapip-sonucu-test-eder.;tc07-istenen-kelimenin-oldugunu-test-etme",
        "after": [
          {
            "result": {
              "duration": 5000600,
              "status": "passed"
            },
            "match": {
              "location": "stepdefinitions.Hooks.tearDown(io.cucumber.java.Scenario)"
            }
          }
        ],
        "type": "scenario",
        "keyword": "Scenario",
        "steps": [
          {
            "result": {
              "duration": 10487972000,
              "status": "passed"
            },
            "line": 6,
            "name": "kullanici \"amazonUrl\" sayfasina gider",
            "match": {
              "arguments": [
                {
                  "val": "\"amazonUrl\"",
                  "offset": 10
                }
              ],
              "location": "stepdefinitions.amazonStepDefinitions.kullaniciSayfasinaGider(java.lang.String)"
            },
            "keyword": "Given "
          },
          {
            "result": {
              "duration": 2404064100,
              "status": "passed"
            },
            "line": 7,
            "name": "\"ipod\" icin arama yapar",
            "match": {
              "arguments": [
                {
                  "val": "\"ipod\"",
                  "offset": 0
                }
              ],
              "location": "stepdefinitions.amazonStepDefinitions.icinAramaYapar(java.lang.String)"
            },
            "keyword": "Then "
          },
          {
            "result": {
              "duration": 150013900,
              "status": "passed"
            },
            "line": 8,
            "name": "sonucun \"ipod\" icerdigini test eder",
            "match": {
              "arguments": [
                {
                  "val": "\"ipod\"",
                  "offset": 8
                }
              ],
              "location": "stepdefinitions.amazonStepDefinitions.sonucunIcerdiginiTestEder(java.lang.String)"
            },
            "keyword": "Then "
          },
          {
            "result": {
              "duration": 658826500,
              "status": "passed"
            },
            "line": 9,
            "name": "sayfayi kapatir",
            "match": {
              "location": "stepdefinitions.amazonStepDefinitions.sayfayi_kapatir()"
            },
            "keyword": "And "
          }
        ],
        "tags": [
          {
            "name": "@Paralel2"
          }
        ]
      }
    ],
    "name": "US1003 Kullanici istedigi kelime icin arama yapip sonucu test eder.",
    "description": "",
    "id": "us1003-kullanici-istedigi-kelime-icin-arama-yapip-sonucu-test-eder.",
    "keyword": "Feature",
    "uri": "file:src/test/resources/features/US1003_amazonParametreliArama.feature",
    "tags": [
      {
        "name": "@Paralel2",
        "type": "Tag",
        "location": {
          "line": 1,
          "column": 1
        }
      }
    ]
  },
  {
    "line": 2,
    "elements": [
      {
        "start_timestamp": "2021-11-11T08:51:04.528Z",
        "before": [
          {
            "result": {
              "status": "passed"
            },
            "match": {
              "location": "stepdefinitions.Hooks.setUp()"
            }
          }
        ],
        "line": 17,
        "name": "TC09 amazonda verilen bir listeyi aratip, var olduklarini test ediniz",
        "description": "",
        "id": "us1005-amazonda-liste-ile-arama;tc09-amazonda-verilen-bir-listeyi-aratip--var-olduklarini-test-ediniz;;2",
        "after": [
          {
            "result": {
              "status": "passed"
            },
            "match": {
              "location": "stepdefinitions.Hooks.tearDown(io.cucumber.java.Scenario)"
            }
          }
        ],
        "type": "scenario",
        "keyword": "Scenario Outline",
        "steps": [
          {
            "result": {
              "duration": 3290557200,
              "status": "passed"
            },
            "line": 6,
            "name": "kullanici \"amazonUrl\" sayfasina gider",
            "match": {
              "arguments": [
                {
                  "val": "\"amazonUrl\"",
                  "offset": 10
                }
              ],
              "location": "stepdefinitions.amazonStepDefinitions.kullaniciSayfasinaGider(java.lang.String)"
            },
            "keyword": "Given "
          },
          {
            "result": {
              "duration": 2540448300,
              "status": "passed"
            },
            "line": 7,
            "name": "\"nutella\" icin arama yapar",
            "match": {
              "arguments": [
                {
                  "val": "\"nutella\"",
                  "offset": 0
                }
              ],
              "location": "stepdefinitions.amazonStepDefinitions.icinAramaYapar(java.lang.String)"
            },
            "keyword": "Then "
          },
          {
            "result": {
              "duration": 98012100,
              "status": "passed"
            },
            "line": 8,
            "name": "sonuc sayisini yazdirir",
            "match": {
              "location": "stepdefinitions.amazonStepDefinitions.sonucSayisiniYazdirir()"
            },
            "keyword": "And "
          },
          {
            "result": {
              "duration": 32012400,
              "status": "passed"
            },
            "line": 9,
            "name": "sonucun \"nutella\" icerdigini test eder",
            "match": {
              "arguments": [
                {
                  "val": "\"nutella\"",
                  "offset": 8
                }
              ],
              "location": "stepdefinitions.amazonStepDefinitions.sonucunIcerdiginiTestEder(java.lang.String)"
            },
            "keyword": "And "
          },
          {
            "result": {
              "duration": 641960100,
              "status": "passed"
            },
            "line": 10,
            "name": "sayfayi kapatir",
            "match": {
              "location": "stepdefinitions.amazonStepDefinitions.sayfayi_kapatir()"
            },
            "keyword": "Then "
          }
        ],
        "tags": [
          {
            "name": "@Paralel2"
          }
        ]
      },
      {
        "start_timestamp": "2021-11-11T08:51:11.164Z",
        "before": [
          {
            "result": {
              "status": "passed"
            },
            "match": {
              "location": "stepdefinitions.Hooks.setUp()"
            }
          }
        ],
        "line": 18,
        "name": "TC09 amazonda verilen bir listeyi aratip, var olduklarini test ediniz",
        "description": "",
        "id": "us1005-amazonda-liste-ile-arama;tc09-amazonda-verilen-bir-listeyi-aratip--var-olduklarini-test-ediniz;;3",
        "after": [
          {
            "result": {
              "status": "passed"
            },
            "match": {
              "location": "stepdefinitions.Hooks.tearDown(io.cucumber.java.Scenario)"
            }
          }
        ],
        "type": "scenario",
        "keyword": "Scenario Outline",
        "steps": [
          {
            "result": {
              "duration": 4339183000,
              "status": "passed"
            },
            "line": 6,
            "name": "kullanici \"amazonUrl\" sayfasina gider",
            "match": {
              "arguments": [
                {
                  "val": "\"amazonUrl\"",
                  "offset": 10
                }
              ],
              "location": "stepdefinitions.amazonStepDefinitions.kullaniciSayfasinaGider(java.lang.String)"
            },
            "keyword": "Given "
          },
          {
            "result": {
              "duration": 2763550700,
              "status": "passed"
            },
            "line": 7,
            "name": "\"java\" icin arama yapar",
            "match": {
              "arguments": [
                {
                  "val": "\"java\"",
                  "offset": 0
                }
              ],
              "location": "stepdefinitions.amazonStepDefinitions.icinAramaYapar(java.lang.String)"
            },
            "keyword": "Then "
          },
          {
            "result": {
              "duration": 111782500,
              "status": "passed"
            },
            "line": 8,
            "name": "sonuc sayisini yazdirir",
            "match": {
              "location": "stepdefinitions.amazonStepDefinitions.sonucSayisiniYazdirir()"
            },
            "keyword": "And "
          },
          {
            "result": {
              "duration": 48016700,
              "status": "passed"
            },
            "line": 9,
            "name": "sonucun \"java\" icerdigini test eder",
            "match": {
              "arguments": [
                {
                  "val": "\"java\"",
                  "offset": 8
                }
              ],
              "location": "stepdefinitions.amazonStepDefinitions.sonucunIcerdiginiTestEder(java.lang.String)"
            },
            "keyword": "And "
          },
          {
            "result": {
              "duration": 608525100,
              "status": "passed"
            },
            "line": 10,
            "name": "sayfayi kapatir",
            "match": {
              "location": "stepdefinitions.amazonStepDefinitions.sayfayi_kapatir()"
            },
            "keyword": "Then "
          }
        ],
        "tags": [
          {
            "name": "@Paralel2"
          }
        ]
      },
      {
        "start_timestamp": "2021-11-11T08:51:19.048Z",
        "before": [
          {
            "result": {
              "duration": 1000300,
              "status": "passed"
            },
            "match": {
              "location": "stepdefinitions.Hooks.setUp()"
            }
          }
        ],
        "line": 19,
        "name": "TC09 amazonda verilen bir listeyi aratip, var olduklarini test ediniz",
        "description": "",
        "id": "us1005-amazonda-liste-ile-arama;tc09-amazonda-verilen-bir-listeyi-aratip--var-olduklarini-test-ediniz;;4",
        "after": [
          {
            "result": {
              "status": "passed"
            },
            "match": {
              "location": "stepdefinitions.Hooks.tearDown(io.cucumber.java.Scenario)"
            }
          }
        ],
        "type": "scenario",
        "keyword": "Scenario Outline",
        "steps": [
          {
            "result": {
              "duration": 4368906000,
              "status": "passed"
            },
            "line": 6,
            "name": "kullanici \"amazonUrl\" sayfasina gider",
            "match": {
              "arguments": [
                {
                  "val": "\"amazonUrl\"",
                  "offset": 10
                }
              ],
              "location": "stepdefinitions.amazonStepDefinitions.kullaniciSayfasinaGider(java.lang.String)"
            },
            "keyword": "Given "
          },
          {
            "result": {
              "duration": 2803508100,
              "status": "passed"
            },
            "line": 7,
            "name": "\"ipod\" icin arama yapar",
            "match": {
              "arguments": [
                {
                  "val": "\"ipod\"",
                  "offset": 0
                }
              ],
              "location": "stepdefinitions.amazonStepDefinitions.icinAramaYapar(java.lang.String)"
            },
            "keyword": "Then "
          },
          {
            "result": {
              "duration": 102942600,
              "status": "passed"
            },
            "line": 8,
            "name": "sonuc sayisini yazdirir",
            "match": {
              "location": "stepdefinitions.amazonStepDefinitions.sonucSayisiniYazdirir()"
            },
            "keyword": "And "
          },
          {
            "result": {
              "duration": 27995500,
              "status": "passed"
            },
            "line": 9,
            "name": "sonucun \"ipod\" icerdigini test eder",
            "match": {
              "arguments": [
                {
                  "val": "\"ipod\"",
                  "offset": 8
                }
              ],
              "location": "stepdefinitions.amazonStepDefinitions.sonucunIcerdiginiTestEder(java.lang.String)"
            },
            "keyword": "And "
          },
          {
            "result": {
              "duration": 626596200,
              "status": "passed"
            },
            "line": 10,
            "name": "sayfayi kapatir",
            "match": {
              "location": "stepdefinitions.amazonStepDefinitions.sayfayi_kapatir()"
            },
            "keyword": "Then "
          }
        ],
        "tags": [
          {
            "name": "@Paralel2"
          }
        ]
      },
      {
        "start_timestamp": "2021-11-11T08:51:26.987Z",
        "before": [
          {
            "result": {
              "status": "passed"
            },
            "match": {
              "location": "stepdefinitions.Hooks.setUp()"
            }
          }
        ],
        "line": 20,
        "name": "TC09 amazonda verilen bir listeyi aratip, var olduklarini test ediniz",
        "description": "",
        "id": "us1005-amazonda-liste-ile-arama;tc09-amazonda-verilen-bir-listeyi-aratip--var-olduklarini-test-ediniz;;5",
        "after": [
          {
            "result": {
              "status": "passed"
            },
            "match": {
              "location": "stepdefinitions.Hooks.tearDown(io.cucumber.java.Scenario)"
            }
          }
        ],
        "type": "scenario",
        "keyword": "Scenario Outline",
        "steps": [
          {
            "result": {
              "duration": 4075146100,
              "status": "passed"
            },
            "line": 6,
            "name": "kullanici \"amazonUrl\" sayfasina gider",
            "match": {
              "arguments": [
                {
                  "val": "\"amazonUrl\"",
                  "offset": 10
                }
              ],
              "location": "stepdefinitions.amazonStepDefinitions.kullaniciSayfasinaGider(java.lang.String)"
            },
            "keyword": "Given "
          },
          {
            "result": {
              "duration": 2490086200,
              "status": "passed"
            },
            "line": 7,
            "name": "\"armut\" icin arama yapar",
            "match": {
              "arguments": [
                {
                  "val": "\"armut\"",
                  "offset": 0
                }
              ],
              "location": "stepdefinitions.amazonStepDefinitions.icinAramaYapar(java.lang.String)"
            },
            "keyword": "Then "
          },
          {
            "result": {
              "duration": 95540500,
              "status": "passed"
            },
            "line": 8,
            "name": "sonuc sayisini yazdirir",
            "match": {
              "location": "stepdefinitions.amazonStepDefinitions.sonucSayisiniYazdirir()"
            },
            "keyword": "And "
          },
          {
            "result": {
              "duration": 56012300,
              "status": "passed"
            },
            "line": 9,
            "name": "sonucun \"armut\" icerdigini test eder",
            "match": {
              "arguments": [
                {
                  "val": "\"armut\"",
                  "offset": 8
                }
              ],
              "location": "stepdefinitions.amazonStepDefinitions.sonucunIcerdiginiTestEder(java.lang.String)"
            },
            "keyword": "And "
          },
          {
            "result": {
              "duration": 667901200,
              "status": "passed"
            },
            "line": 10,
            "name": "sayfayi kapatir",
            "match": {
              "location": "stepdefinitions.amazonStepDefinitions.sayfayi_kapatir()"
            },
            "keyword": "Then "
          }
        ],
        "tags": [
          {
            "name": "@Paralel2"
          }
        ]
      },
      {
        "start_timestamp": "2021-11-11T08:51:34.384Z",
        "before": [
          {
            "result": {
              "status": "passed"
            },
            "match": {
              "location": "stepdefinitions.Hooks.setUp()"
            }
          }
        ],
        "line": 21,
        "name": "TC09 amazonda verilen bir listeyi aratip, var olduklarini test ediniz",
        "description": "",
        "id": "us1005-amazonda-liste-ile-arama;tc09-amazonda-verilen-bir-listeyi-aratip--var-olduklarini-test-ediniz;;6",
        "after": [
          {
            "result": {
              "status": "passed"
            },
            "match": {
              "location": "stepdefinitions.Hooks.tearDown(io.cucumber.java.Scenario)"
            }
          }
        ],
        "type": "scenario",
        "keyword": "Scenario Outline",
        "steps": [
          {
            "result": {
              "duration": 3696076100,
              "status": "passed"
            },
            "line": 6,
            "name": "kullanici \"amazonUrl\" sayfasina gider",
            "match": {
              "arguments": [
                {
                  "val": "\"amazonUrl\"",
                  "offset": 10
                }
              ],
              "location": "stepdefinitions.amazonStepDefinitions.kullaniciSayfasinaGider(java.lang.String)"
            },
            "keyword": "Given "
          },
          {
            "result": {
              "duration": 1981968900,
              "status": "passed"
            },
            "line": 7,
            "name": "\"Apple\" icin arama yapar",
            "match": {
              "arguments": [
                {
                  "val": "\"Apple\"",
                  "offset": 0
                }
              ],
              "location": "stepdefinitions.amazonStepDefinitions.icinAramaYapar(java.lang.String)"
            },
            "keyword": "Then "
          },
          {
            "result": {
              "duration": 115846700,
              "status": "passed"
            },
            "line": 8,
            "name": "sonuc sayisini yazdirir",
            "match": {
              "location": "stepdefinitions.amazonStepDefinitions.sonucSayisiniYazdirir()"
            },
            "keyword": "And "
          },
          {
            "result": {
              "duration": 60015000,
              "status": "passed"
            },
            "line": 9,
            "name": "sonucun \"Apple\" icerdigini test eder",
            "match": {
              "arguments": [
                {
                  "val": "\"Apple\"",
                  "offset": 8
                }
              ],
              "location": "stepdefinitions.amazonStepDefinitions.sonucunIcerdiginiTestEder(java.lang.String)"
            },
            "keyword": "And "
          },
          {
            "result": {
              "duration": 616914900,
              "status": "passed"
            },
            "line": 10,
            "name": "sayfayi kapatir",
            "match": {
              "location": "stepdefinitions.amazonStepDefinitions.sayfayi_kapatir()"
            },
            "keyword": "Then "
          }
        ],
        "tags": [
          {
            "name": "@Paralel2"
          }
        ]
      }
    ],
    "name": "US1005 amazonda liste ile arama",
    "description": "",
    "id": "us1005-amazonda-liste-ile-arama",
    "keyword": "Feature",
    "uri": "file:src/test/resources/features/US1005_scenarioOutline.feature",
    "tags": [
      {
        "name": "@Paralel2",
        "type": "Tag",
        "location": {
          "line": 1,
          "column": 1
        }
      }
    ]
  }
]